{
  "name": "@vef/easy-api",
  "version": "0.2.5",
  "exports": {
    ".": "./mod.ts",
    "./api": "./src/easyApi.ts",
    "./types": "./src/types.ts",
    "./src/types.ts": "./src/types.ts",
    "./src/easyApi.ts": "./src/easyApi.ts"
  },
  "tasks": {
    "check": "deno publish --dry-run"
  },
  "publish": {
    "exclude": [
      ".github"
    ],
    "include": [
      "mod.ts",
      "src",
      "LICENSE",
      "README.md"
    ]
  },
  "imports": {
    "@vef/easy-orm": "jsr:@vef/easy-orm@^0.3.12"
  }
}
